chess-cheat.py
chess_cheat_utils/__init__.py
chess_cheat_utils/board.py
chess_cheat_utils/finder.py
chess_cheat_utils/model.pb
chess_cheat_utils/utils.py
chess_cheat-1.0.3.dist-info/METADATA
chess_cheat-1.0.3.dist-info/WHEEL
chess_cheat-1.0.3.dist-info/top_level.txt
chess_cheat-1.0.3.dist-info/RECORD
