Metadata-Version: 2.1
Name: chess-cheat
Version: 1.0.3
Summary: Chess-Cheat is a tool to cheat at online chess
Home-page: https://github.com/GabrieleMaurina/chess-cheat
Author: Gabriele Maurina
Author-email: gabrielemaurina95@gmail.com
License: MIT
Platform: UNKNOWN
Classifier: Programming Language :: Python :: 3
Classifier: License :: OSI Approved :: MIT License
Classifier: Operating System :: OS Independent
Requires-Python: >=3.8
Requires-Dist: tensorflow
Requires-Dist: stockfish
Requires-Dist: pillow
Requires-Dist: pyscreenshot
Requires-Dist: timeout-decorator
Requires-Dist: numpy
